ai_assistantbot/__init__.py
ai_assistantbot/assistant.py
ai_assistantbot-0.0.11.dist-info/LICENSE
ai_assistantbot-0.0.11.dist-info/METADATA
ai_assistantbot-0.0.11.dist-info/WHEEL
ai_assistantbot-0.0.11.dist-info/top_level.txt
ai_assistantbot-0.0.11.dist-info/RECORD
