Metadata-Version: 2.1
Name: ai-assistantbot
Version: 0.0.11
Summary: AssistantBot is a python package which provides an question-answering system designed to process large datasets efficiently. It dynamically matches user queries with relevant data, offering accurate responses and easy training process.
Home-page: https://github.com/wassim-khleifi/ai_assistantbot
Author: Wassim Khleifi
Author-email: wassimkhleifi@gamil.com
License: UNKNOWN
Platform: UNKNOWN
Classifier: Programming Language :: Python :: 3
Classifier: License :: OSI Approved :: MIT License
Classifier: Operating System :: OS Independent
Requires-Python: >=3.8
